barvocuc/COPYING.html
barvocuc/__init__.py
barvocuc/__main__.py
barvocuc/analysis.py
barvocuc/batch.py
barvocuc/cli.py
barvocuc/gui.py
barvocuc/settings.py
barvocuc/media/default.png
barvocuc/translations/barvocuc.cs_CZ.qm
barvocuc/translations/barvocuc.cs_CZ.ts
barvocuc/translations/barvocuc.en_US.qm
barvocuc/translations/barvocuc.en_US.ts
barvocuc/ui/about.ui
barvocuc/ui/mainwindow.ui
barvocuc-2.0.dist-info/DESCRIPTION.rst
barvocuc-2.0.dist-info/METADATA
barvocuc-2.0.dist-info/RECORD
barvocuc-2.0.dist-info/WHEEL
barvocuc-2.0.dist-info/entry_points.txt
barvocuc-2.0.dist-info/metadata.json
barvocuc-2.0.dist-info/top_level.txt
